prospyr/__init__.py
prospyr/cache.py
prospyr/connection.py
prospyr/exceptions.py
prospyr/fields.py
prospyr/mixins.py
prospyr/resources.py
prospyr/schema.py
prospyr/search.py
prospyr/util.py
prospyr/validate.py
prospyr/version.py
prospyr-0.8.0.dist-info/DESCRIPTION.rst
prospyr-0.8.0.dist-info/METADATA
prospyr-0.8.0.dist-info/RECORD
prospyr-0.8.0.dist-info/WHEEL
prospyr-0.8.0.dist-info/metadata.json
prospyr-0.8.0.dist-info/top_level.txt
