Metadata-Version: 2.0
Name: prospyr
Version: 0.8.0
Summary: ProsperWorks client library
Home-page: https://github.com/salespreso/prospyr/
Author: Ben Graham
Author-email: ben.graham@salespreso.com
License: MIT
Keywords: ProsperWorks
Platform: UNKNOWN
Classifier: Intended Audience :: Developers
Classifier: Programming Language :: Python :: 2
Classifier: Programming Language :: Python :: 2.7
Classifier: Programming Language :: Python :: 3
Classifier: Programming Language :: Python :: 3.4
Classifier: Programming Language :: Python :: 3.5
Requires-Dist: arrow
Requires-Dist: marshmallow
Requires-Dist: requests
Requires-Dist: six
Requires-Dist: urlobject
Provides-Extra: dev
Requires-Dist: coverage; extra == 'dev'
Requires-Dist: flake8; extra == 'dev'
Requires-Dist: ipdb; extra == 'dev'
Requires-Dist: isort; extra == 'dev'
Requires-Dist: mock; extra == 'dev'
Requires-Dist: nose; extra == 'dev'
Requires-Dist: rednose; extra == 'dev'
Requires-Dist: twine; extra == 'dev'
Requires-Dist: tox; extra == 'dev'
